{
  "project_info": {
    "project_number": "776928409291",
    "project_id": "krishisuvidha-67c5a",
    "storage_bucket": "krishisuvidha-67c5a.appspot.com"
  },
  "client": [
    {
      "client_info": {
        "mobilesdk_app_id": "1:776928409291:android:8478ddb2d1ce7bfdf70d4e",
        "android_client_info": {
          "package_name": "com.example.firebase_tset"
        }
      },
      "oauth_client": [],
      "api_key": [
        {
          "current_key": "AIzaSyBqv3o51OOLAFdBiYuNRrebzAl3A_qIuI0"
        }
      ],
      "services": {
        "appinvite_service": {
          "other_platform_oauth_client": []
        }
      }
    }
  ],
  "configuration_version": "1"
}